{
  "title": "HTML Injection",
  "breadcrumb": [
    {
      "name": "Bug Bounty Reports & Articles",
      "url": "/docs/bug-bounty-reports-and-articles"
    },
    {
      "name": "Injections (HTML, XSS, etc)",
      "url": "/docs/bug-bounty-reports-and-articles/injections-html-xss-etc",
      "icon": "6️⃣"
    }
  ],
  "sections": [
    {
      "type": "link_card",
      "title": "https://hackerone.com/reports/181810",
      "url": "https://hackerone.com/reports/181810"
    },
    {
      "type": "link_card",
      "title": "X / xAI disclosed on HackerOne: Html Injection and Possible XSS via...",
      "url": "https://hackerone.com/reports/502926",
      "logo": "https://Penquin.gitbook.io/docs/~gitbook/image?url=https%3A%2F%2Fhackerone.com%2Ffavicon.ico&width=20&dpr=3&quality=100&sign=39079eb2&sv=2"
    },
    {
      "type": "link_card",
      "title": "X / xAI disclosed on HackerOne: Html Injection and Possible XSS in...",
      "url": "https://hackerone.com/reports/150179",
      "logo": "https://Penquin.gitbook.io/docs/~gitbook/image?url=https%3A%2F%2Fhackerone.com%2Ffavicon.ico&width=20&dpr=3&quality=100&sign=39079eb2&sv=2"
    },
    {
      "type": "link_card",
      "title": "Concrete CMS disclosed on HackerOne: Unauthenticated HTML Injection...",
      "url": "https://hackerone.com/reports/768327",
      "logo": "https://Penquin.gitbook.io/docs/~gitbook/image?url=https%3A%2F%2Fhackerone.com%2Ffavicon.ico&width=20&dpr=3&quality=100&sign=39079eb2&sv=2"
    },
    {
      "type": "link_card",
      "title": "Simple HTML Injection to $250",
      "url": "https://medium.com/@chaitanyarajhans024/simple-html-injection-to-250-895b760409ed",
      "logo": "https://Penquin.gitbook.io/docs/~gitbook/image?url=https%3A%2F%2Fmiro.medium.com%2Fv2%2Fresize%3Afill%3A304%3A304%2F10fd5c419ac61637245384e7099e131627900034828f4f386bdaa47a74eae156&width=20&dpr=3&quality=100&sign=7ce5f3bc&sv=2"
    },
    {
      "type": "link_card",
      "title": "All you need to know about HTML Injection",
      "url": "https://medium.com/@sathvika03/all-you-need-to-know-about-html-injection-4f8cd71e1dfa",
      "logo": "https://Penquin.gitbook.io/docs/~gitbook/image?url=https%3A%2F%2Fmiro.medium.com%2Fv2%2Fresize%3Afill%3A304%3A304%2F10fd5c419ac61637245384e7099e131627900034828f4f386bdaa47a74eae156&width=20&dpr=3&quality=100&sign=7ce5f3bc&sv=2"
    },
    {
      "type": "link_card",
      "title": "Methods to Exploit HTML Injection",
      "url": "https://corneacristian.medium.com/methods-to-exploit-html-injection-17b4254035e",
      "logo": "https://Penquin.gitbook.io/docs/~gitbook/image?url=https%3A%2F%2Fmiro.medium.com%2Fv2%2Fresize%3Afill%3A304%3A304%2F10fd5c419ac61637245384e7099e131627900034828f4f386bdaa47a74eae156&width=20&dpr=3&quality=100&sign=7ce5f3bc&sv=2"
    },
    {
      "type": "link_card",
      "title": "HTML Injection",
      "url": "https://ms-official5878.medium.com/html-injection-a3f791d31b3c",
      "logo": "https://Penquin.gitbook.io/docs/~gitbook/image?url=https%3A%2F%2Fmiro.medium.com%2Fv2%2Fresize%3Afill%3A304%3A304%2F10fd5c419ac61637245384e7099e131627900034828f4f386bdaa47a74eae156&width=20&dpr=3&quality=100&sign=7ce5f3bc&sv=2"
    },
    {
      "type": "video",
      "url": "https://cdn.iframe.ly/DAbBCDH"
    },
    {
      "type": "video",
      "url": "https://cdn.iframe.ly/ea4wYLg"
    }
  ],
  "navigation": {
    "previous": {
      "title": "XSS",
      "url": "/docs/bug-bounty-reports-and-articles/injections-html-xss-etc/xss"
    },
    "next": {
      "title": "SQL Injection",
      "url": "/docs/bug-bounty-reports-and-articles/injections-html-xss-etc/sql-injection"
    }
  },
  "metadata": {
    "lastUpdated": "2024-06-29T06:31:42.156Z"
  }
}
